uroman/__init__.py
uroman/uroman-pl/.git
uroman/uroman-pl/.gitignore
uroman/uroman-pl/LICENSE.txt
uroman/uroman-pl/README.md
uroman/uroman-pl/README.txt
uroman/uroman-pl/bin/de-accent.pl
uroman/uroman-pl/bin/string-distance.pl
uroman/uroman-pl/bin/uroman-quick.pl
uroman/uroman-pl/bin/uroman-tsv.sh
uroman/uroman-pl/bin/uroman.pl
uroman/uroman-pl/data/Chinese_to_Pinyin.txt
uroman/uroman-pl/data/Scripts.txt
uroman/uroman-pl/data/UnicodeData.txt
uroman/uroman-pl/data/UnicodeDataOverwrite.txt
uroman/uroman-pl/data/romanization-table-arabic-block.txt
uroman/uroman-pl/data/romanization-table.txt
uroman/uroman-pl/data/romanization-table.v1.2.1.txt
uroman/uroman-pl/data/string-distance-cost-rules.txt
uroman/uroman-pl/lib/JSON.pm
uroman/uroman-pl/lib/JSON/backportPP.pm
uroman/uroman-pl/lib/NLP/Chinese.pm
uroman/uroman-pl/lib/NLP/English.pm
uroman/uroman-pl/lib/NLP/Romanizer.pm
uroman/uroman-pl/lib/NLP/UTF8.pm
uroman/uroman-pl/lib/NLP/stringDistance.pm
uroman/uroman-pl/lib/NLP/utilities.pm
uroman_python-1.2.8.1.dist-info/METADATA
uroman_python-1.2.8.1.dist-info/WHEEL
uroman_python-1.2.8.1.dist-info/top_level.txt
uroman_python-1.2.8.1.dist-info/RECORD
